<?xml version="1.0" encoding="UTF-8"?>

<info>
<author>stevenda
  <email>stevenda@cs.cmu.edu</email>
</author>
<url>https://github.com/LearnSphere/WorkflowComponents/tree/master/ProblemCreator</url>
<date>July 18, 2019</date>
<abstract>The <b>ProblemCreator</b> component is an example of a(n) Python component.</abstract>
<description>Allow user to create a new problem given a problem wizard</description>

<inputs>
</inputs>

<outputs>
<b>problem</b>
<b>ranked-models</b>
<b>inline-html</b>
</outputs>

<options>
</options>

</info>
